Topsis/__init__.py
Topsis/topsis.py
Topsis_Khwaish_102217010-1.0.1.dist-info/LICENSE.txt
Topsis_Khwaish_102217010-1.0.1.dist-info/METADATA
Topsis_Khwaish_102217010-1.0.1.dist-info/WHEEL
Topsis_Khwaish_102217010-1.0.1.dist-info/entry_points.txt
Topsis_Khwaish_102217010-1.0.1.dist-info/top_level.txt
Topsis_Khwaish_102217010-1.0.1.dist-info/RECORD
