Metadata-Version: 2.2
Name: Topsis-Khwaish-102217010
Version: 1.0.1
Summary: A Python package to perform TOPSIS analysis
Home-page: https://github.com/khwaishagarwal/Topsis-Khwaish-102217010
Download-URL: https://github.com/khwaishagarwal/Topsis-Khwaish-102217010/archive/refs/tags/v1.0.1.tar.gz
Author: Khwaish Agarwal
Author-email: khwaishagarwal22@gmail.com
License: MIT
Classifier: Programming Language :: Python :: 3
Classifier: License :: OSI Approved :: MIT License
Classifier: Operating System :: OS Independent
Requires-Python: >=3.6
License-File: LICENSE.txt
Requires-Dist: pandas
Requires-Dist: numpy
Dynamic: author
Dynamic: author-email
Dynamic: classifier
Dynamic: description
Dynamic: description-content-type
Dynamic: download-url
Dynamic: home-page
Dynamic: license
Dynamic: requires-dist
Dynamic: requires-python
Dynamic: summary
